boilerplate/__init__.py
boilerplate/__init__.pyc
boilerplate/cmdline.py
boilerplate/cmdline.pyc
boilerplate/conf.py
boilerplate/conf.pyc
boilerplate/filematchers.py
boilerplate/filematchers.pyc
boilerplate/importlib.py
boilerplate/importlib.pyc
boilerplate/shell.py
boilerplate/shell.pyc
boilerplate/template.py
boilerplate/template.pyc
boilerplate/utils.py
boilerplate/utils.pyc
boilerplate/__pycache__/__init__.cpython-35.pyc
boilerplate/__pycache__/cmdline.cpython-35.pyc
boilerplate/__pycache__/conf.cpython-35.pyc
boilerplate/__pycache__/filematchers.cpython-35.pyc
boilerplate/__pycache__/importlib.cpython-35.pyc
boilerplate/__pycache__/shell.cpython-35.pyc
boilerplate/__pycache__/template.cpython-35.pyc
boilerplate/__pycache__/utils.cpython-35.pyc
boilerplate/tmpl/__init__.py
boilerplate/tmpl/boil_template/__init__.py
boilerplate/tmpl/boil_template/config.py
boilerplate/tmpl/boil_template/tmpl/_$project_name$_/__init__.py
boilerplate/tmpl/boil_template/tmpl/_$project_name$_/config.py
boilerplate/tmpl/boil_template/tmpl/_$project_name$_/tmpl/_$project_name_var$_/_$project_name_var$__readme.txt
boilerplate-1.2.4.data/scripts/boil
boilerplate-1.2.4.dist-info/AUTHORS.rst
boilerplate-1.2.4.dist-info/METADATA
boilerplate-1.2.4.dist-info/WHEEL
boilerplate-1.2.4.dist-info/top_level.txt
boilerplate-1.2.4.dist-info/RECORD
