Metadata-Version: 2.1
Name: boilerplate
Version: 1.2.4
Summary: Easy to use tool for painless project layout templating
Home-page: https://github.com/jqb/boilerplate/tree/ver-1.2.4
Author: Kuba Janoszek
Author-email: kuba.janoszek@gmail.com
License: UNKNOWN
Platform: UNKNOWN
Classifier: Development Status :: 3 - Alpha
Classifier: Environment :: Web Environment
Classifier: Intended Audience :: Developers
Classifier: License :: OSI Approved :: BSD License
Classifier: Operating System :: OS Independent
Classifier: Programming Language :: Python
